<?xml version="1.0" encoding="UTF-8"?>
<SOAP-ENV:Envelope
 xmlns:SOAP-ENV="http://www.w3.org/2003/05/soap-envelope"
 xmlns:SOAP-ENC="http://www.w3.org/2003/05/soap-encoding"
 xmlns:xsi="http://www.w3.org/2001/XMLSchema-instance"
 xmlns:xsd="http://www.w3.org/2001/XMLSchema"
 xmlns:ns2="http://merchant.happycz.com.cn/BatchServiceSoap"
 xmlns:ns1="http://merchant.happycz.com.cn"
 xmlns:ns3="http://merchant.happycz.com.cn/BatchServiceSoap12">
 <SOAP-ENV:Body>
  <ns1:BatchInResponse>
   <ns1:BatchInResult>
    <ns1:Count>0</ns1:Count>
    <ns1:ErrCode></ns1:ErrCode>
    <ns1:ReturnRecords>
     <ns1:ReturnRecord>
      <ns1:ProjectId></ns1:ProjectId>
      <ns1:BatchId></ns1:BatchId>
      <ns1:BatchName></ns1:BatchName>
      <ns1:Cr_Code></ns1:Cr_Code>
      <ns1:Amounts>0</ns1:Amounts>
      <ns1:PayAmount>0</ns1:PayAmount>
      <ns1:ReceiveAmount>0</ns1:ReceiveAmount>
      <ns1:Flag></ns1:Flag>
      <ns1:Sign></ns1:Sign>
     </ns1:ReturnRecord>
     <ns1:ReturnRecord>
      <ns1:ProjectId></ns1:ProjectId>
      <ns1:BatchId></ns1:BatchId>
      <ns1:BatchName></ns1:BatchName>
      <ns1:Cr_Code></ns1:Cr_Code>
      <ns1:Amounts>0</ns1:Amounts>
      <ns1:PayAmount>0</ns1:PayAmount>
      <ns1:ReceiveAmount>0</ns1:ReceiveAmount>
      <ns1:Flag></ns1:Flag>
      <ns1:Sign></ns1:Sign>
     </ns1:ReturnRecord>
    </ns1:ReturnRecords>
    <ns1:ReturnRecordSubs>
     <ns1:ReturnRecordSub>
      <ns1:DetailsNew></ns1:DetailsNew>
      <ns1:AmountsNew>0</ns1:AmountsNew>
      <ns1:PayAmountNew>0</ns1:PayAmountNew>
      <ns1:ReceiveAmountNew>0</ns1:ReceiveAmountNew>
     </ns1:ReturnRecordSub>
     <ns1:ReturnRecordSub>
      <ns1:DetailsNew></ns1:DetailsNew>
      <ns1:AmountsNew>0</ns1:AmountsNew>
      <ns1:PayAmountNew>0</ns1:PayAmountNew>
      <ns1:ReceiveAmountNew>0</ns1:ReceiveAmountNew>
     </ns1:ReturnRecordSub>
    </ns1:ReturnRecordSubs>
   </ns1:BatchInResult>
  </ns1:BatchInResponse>
 </SOAP-ENV:Body>
</SOAP-ENV:Envelope>
